LICENSE
MANIFEST.in
README.md
pyproject.toml
setup.py
src/opal_fetcher_postgres/__init__.py
src/opal_fetcher_postgres/provider.py
src/opal_fetcher_postgres/providerNew.py
src/opal_fetcher_postgres_sankar1.egg-info/PKG-INFO
src/opal_fetcher_postgres_sankar1.egg-info/SOURCES.txt
src/opal_fetcher_postgres_sankar1.egg-info/dependency_links.txt
src/opal_fetcher_postgres_sankar1.egg-info/requires.txt
src/opal_fetcher_postgres_sankar1.egg-info/top_level.txt