Metadata-Version: 2.1
Name: opal-fetcher-postgres-sankar1
Version: 0.0.4
Summary: An OPAL fetch provider to bring authorization state from Postgres DB.
Author-email: Sankar V <sankar.v@walmart.com>
License: Apache-2.0
Project-URL: Source, https://github.com/permitio/opal-fetcher-postgres
Project-URL: Bug Tracker, https://github.com/permitio/opal-fetcher-postgres/issues
Keywords: Open Policy Agent,OPA,OPAL,Open Policy Administration Layer,Postgres,Permit.io
Classifier: Operating System :: OS Independent
Classifier: License :: OSI Approved :: Apache Software License
Classifier: Topic :: Software Development :: Libraries :: Python Modules
Classifier: Programming Language :: Python
Classifier: Programming Language :: Python :: 3
Classifier: Programming Language :: Python :: 3.7
Classifier: Programming Language :: Python :: 3.8
Classifier: Programming Language :: Python :: 3.9
Requires-Python: >=3.7
License-File: LICENSE
